AndroidKongjianCaozuoErshisiZhangjing/README.md
AndroidKongjianCaozuoErshisiZhangjing/__init__.py
AndroidKongjianCaozuoErshisiZhangjing/__main__.py
AndroidKongjianCaozuoErshisiZhangjing/file.epub
AndroidKongjianCaozuoErshisiZhangjing/index.html
AndroidKongjianCaozuoErshisiZhangjing/css/__init__.py
AndroidKongjianCaozuoErshisiZhangjing/css/annotations.css
AndroidKongjianCaozuoErshisiZhangjing/css/main.css
AndroidKongjianCaozuoErshisiZhangjing/css/normalize.css
AndroidKongjianCaozuoErshisiZhangjing/css/popup.css
AndroidKongjianCaozuoErshisiZhangjing/font/__init__.py
AndroidKongjianCaozuoErshisiZhangjing/font/fontello.eot
AndroidKongjianCaozuoErshisiZhangjing/font/fontello.svg
AndroidKongjianCaozuoErshisiZhangjing/font/fontello.ttf
AndroidKongjianCaozuoErshisiZhangjing/font/fontello.woff
AndroidKongjianCaozuoErshisiZhangjing/img/__init__.py
AndroidKongjianCaozuoErshisiZhangjing/img/annotator-glyph-sprite.png
AndroidKongjianCaozuoErshisiZhangjing/img/annotator-icon-sprite.png
AndroidKongjianCaozuoErshisiZhangjing/img/apple-touch-icon.png
AndroidKongjianCaozuoErshisiZhangjing/img/cancelfullscreen.png
AndroidKongjianCaozuoErshisiZhangjing/img/close.png
AndroidKongjianCaozuoErshisiZhangjing/img/fullscreen.png
AndroidKongjianCaozuoErshisiZhangjing/img/loader.gif
AndroidKongjianCaozuoErshisiZhangjing/img/menu-icon.png
AndroidKongjianCaozuoErshisiZhangjing/img/save.png
AndroidKongjianCaozuoErshisiZhangjing/img/saved.png
AndroidKongjianCaozuoErshisiZhangjing/img/settings-s.png
AndroidKongjianCaozuoErshisiZhangjing/img/settings.png
AndroidKongjianCaozuoErshisiZhangjing/img/star.png
AndroidKongjianCaozuoErshisiZhangjing/js/__init__.py
AndroidKongjianCaozuoErshisiZhangjing/js/epub.js
AndroidKongjianCaozuoErshisiZhangjing/js/epub.min.js
AndroidKongjianCaozuoErshisiZhangjing/js/epub.min.map
AndroidKongjianCaozuoErshisiZhangjing/js/hooks.min.js
AndroidKongjianCaozuoErshisiZhangjing/js/hooks.min.map
AndroidKongjianCaozuoErshisiZhangjing/js/reader.js
android_kongjian_caozuo_ershisi_zhangjing-2024.3.3.0.dist-info/METADATA
android_kongjian_caozuo_ershisi_zhangjing-2024.3.3.0.dist-info/WHEEL
android_kongjian_caozuo_ershisi_zhangjing-2024.3.3.0.dist-info/entry_points.txt
android_kongjian_caozuo_ershisi_zhangjing-2024.3.3.0.dist-info/top_level.txt
android_kongjian_caozuo_ershisi_zhangjing-2024.3.3.0.dist-info/RECORD
